examplelspserver/__init__.py
examplelspserver/__main__.py
examplelspserver/server.py
examplelspserver/cst/__init__.py
examplelspserver/cst/diagnostic_listener.py
examplelspserver/cst/symbol_table_visitor.py
examplelspserver/cst/verbose_listener.py
examplelspserver/filewriter/__init__.py
examplelspserver/gen/python/TestExprCore/TestExprCoreLexer.py
examplelspserver/gen/python/TestExprCore/TestExprCoreListener.py
examplelspserver/gen/python/TestExprCore/TestExprCoreParser.py
examplelspserver/gen/python/TestExprCore/TestExprCoreVisitor.py
examplelspserver/gen/python/exampleDsl/exampleDslLexer.py
examplelspserver/gen/python/exampleDsl/exampleDslListener.py
examplelspserver/gen/python/exampleDsl/exampleDslParser.py
examplelspserver/gen/python/exampleDsl/exampleDslVisitor.py
examplelspserver/symboltable/__init__.py
examplelspserver/symboltable/symbol_table.py
examplelspserver/utils/__init__.py
examplelspserver/utils/compute_token_index.py
examplelspserver/utils/suggest_variables.py
tests/__init__.py
tests/test_SymbolTable.py
tests/test_VerboseListener_pytest.py
tests/test_VerboseListener_unittest.py
tests/test_features.py
Example_Language-0.40.0.dist-info/LICENSE.txt
Example_Language-0.40.0.dist-info/METADATA
Example_Language-0.40.0.dist-info/WHEEL
Example_Language-0.40.0.dist-info/entry_points.txt
Example_Language-0.40.0.dist-info/top_level.txt
Example_Language-0.40.0.dist-info/RECORD
