Metadata-Version: 2.1
Name: Example-Language
Version: 0.40.0
Summary: A test dsl of the OceanDSL project.
Author-email: sgu <sgu@informatik.uni-kiel.de>
License: Apache License (2.0)
Project-URL: oceandsl · GitLab, https://git.se.informatik.uni-kiel.de/oceandsl
Project-URL: OceanDSL · GitHub, https://github.com/OceanDSL
Classifier: Development Status :: 3 - Alpha
Classifier: Programming Language :: Python :: 3.10
Classifier: Intended Audience :: Developers
Classifier: License :: OSI Approved :: Apache Software License
Classifier: Operating System :: OS Independent
Classifier: Topic :: Software Development
Requires-Python: >=3.10
License-File: LICENSE.txt
Requires-Dist: odsllib >=0.38
